jatools/__init__.py
jatools/decorators.py
jatools/maths.py
jatools/mathtex.py
jatools/plotting.py
jatools/sigsys.py
jatools/unittests/test_maths.py
jatools-0.1.1.dist-info/LICENSE
jatools-0.1.1.dist-info/METADATA
jatools-0.1.1.dist-info/WHEEL
jatools-0.1.1.dist-info/top_level.txt
jatools-0.1.1.dist-info/RECORD
